MANIFEST.in
README.rst
requirements.txt
setup.cfg
setup.py
test_requirements.txt
pyebox/__init__.py
pyebox/__main__.py
pyebox/client.py
pyebox.egg-info/PKG-INFO
pyebox.egg-info/SOURCES.txt
pyebox.egg-info/dependency_links.txt
pyebox.egg-info/entry_points.txt
pyebox.egg-info/requires.txt
pyebox.egg-info/top_level.txt