Metadata-Version: 1.1
Name: pyebox
Version: 1.1.3
Summary: Get your EBox consumption (wwww.ebox.ca)
Home-page: http://github.com/titilambert/pyebox
Author: Thibault Cohen
Author-email: titilambert@gmail.com
License: Apache 2.0
Platform: UNKNOWN
Classifier: Programming Language :: Python :: 3.4
Classifier: Programming Language :: Python :: 3.5
Classifier: Programming Language :: Python :: 3.6
